[
    {
        "nid": "HurricaneMaul",
        "name": "Hurricane Maul",
        "desc": "Always attacks last. Cannot double or counter. Break regardless of enemy weapon on hit. Uses Magic and targets enemy Resistance.",
        "icon_nid": "wexp_icons",
        "icon_index": [
            0,
            2
        ],
        "components": [
            [
                "weapon",
                null
            ],
            [
                "value",
                3000
            ],
            [
                "target_enemy",
                null
            ],
            [
                "min_range",
                1
            ],
            [
                "max_range",
                1
            ],
            [
                "damage",
                20
            ],
            [
                "hit",
                70
            ],
            [
                "crit",
                0
            ],
            [
                "weight",
                15
            ],
            [
                "level_exp",
                null
            ],
            [
                "weapon_type",
                "Axe"
            ],
            [
                "weapon_rank",
                "B"
            ],
            [
                "status_on_equip",
                "Fort"
            ],
            [
                "cannot_counter",
                null
            ],
            [
                "no_double",
                null
            ],
            [
                "alternate_damage_formula",
                "MAGIC_DAMAGE"
            ],
            [
                "alternate_resist_formula",
                "MAGIC_DEFENSE"
            ]
        ]
    }
]