[
    {
        "nid": "Kaiserschwert",
        "name": "Kaiserschwert",
        "desc": "Rhodys only. Its true power is yet locked away...",
        "icon_nid": "KaiserSchwert",
        "icon_index": [
            0,
            0
        ],
        "components": [
            [
                "weapon",
                null
            ],
            [
                "target_enemy",
                null
            ],
            [
                "min_range",
                1
            ],
            [
                "max_range",
                1
            ],
            [
                "damage",
                9
            ],
            [
                "hit",
                90
            ],
            [
                "crit",
                10
            ],
            [
                "weight",
                7
            ],
            [
                "level_exp",
                null
            ],
            [
                "weapon_type",
                "Sword"
            ],
            [
                "prf_unit",
                [
                    "Rhodys"
                ]
            ]
        ]
    }
]